{
  "sources": [
    {
      "id": "cdc_travel_notices",
      "name": "CDC Travel Notices",
      "type": "rss",
      "enabled": true,
      "url": "https://wwwnc.cdc.gov/travel/rss/notices.xml"
    },
    {
      "id": "cdc_newsroom",
      "name": "CDC Newsroom",
      "type": "rss",
      "enabled": true,
      "url": "https://tools.cdc.gov/api/v2/resources/media/132608.rss"
    },
    {
      "id": "who_emro",
      "name": "WHO EMRO RSS",
      "type": "rss",
      "enabled": true,
      "url": "https://www.emro.who.int/rss-feeds.html"
    },
    {
      "id": "saudi_moh_news",
      "name": "Saudi MOH News",
      "type": "rss",
      "enabled": true,
      "url": "https://www.moh.gov.sa/_layouts/15/moh/RssGenerator.aspx?WebSiteUrl=/Ministry/MediaCenter/News/&ListUrl=/Ministry/MediaCenter/News/Pages/&ViewName=RSSView&RssTitle=&RssDescription=&DescriptionField=BriefDesc"
    },
    {
      "id": "saudi_moh_tips",
      "name": "Saudi MOH Health Tips",
      "type": "rss",
      "enabled": true,
      "url": "https://www.moh.gov.sa/_layouts/15/moh/RssGenerator.aspx?WebSiteUrl=/HealthAwareness/EducationalContent/HealthTips/&ListUrl=/HealthAwareness/EducationalContent/HealthTips/Pages/&ViewName=RSSView&RssTitle=&RssDescription=BriefDesc"
    },
    {
      "id": "bahrain_moh",
      "name": "Bahrain MOH Health Info",
      "type": "rss",
      "enabled": true,
      "url": "https://www.moh.gov.bh/HealthInfo/RSS"
    },
    {
      "id": "saudi_sfda",
      "name": "Saudi SFDA Health News",
      "type": "rss",
      "enabled": true,
      "url": "https://www.sfda.gov.sa/ar/news.xml?tags=1"
    },
    {
      "id": "cnn_arabic_health",
      "name": "CNN Arabic Health & Science",
      "type": "rss",
      "enabled": true,
      "url": "https://arabic.cnn.com/rss/sections/science-and-health.rss"
    },
    {
      "id": "sky_news_arabia_health",
      "name": "Sky News Arabia Health",
      "type": "rss",
      "enabled": true,
      "url": "https://www.skynewsarabia.com/rss/v1/section/health"
    },
    {
      "id": "alarabiya_healthy_living",
      "name": "Al Arabiya Healthy Living",
      "type": "rss",
      "enabled": true,
      "url": "https://www.alarabiya.net/feed/rss/lifestyle/healthy-living"
    },
    {
      "id": "asharq_health",
      "name": "Asharq News Health",
      "type": "rss",
      "enabled": true,
      "url": "https://asharq.com/rss/health"
    },
    {
      "id": "bbc_arabic_world",
      "name": "BBC Arabic World News",
      "type": "rss",
      "enabled": true,
      "url": "https://www.bbc.com/arabic/index.xml"
    },
    {
      "id": "youm7_medicine",
      "name": "Youm7 Medicine & Health",
      "type": "rss",
      "enabled": true,
      "url": "https://www.youm7.com/rss/Section?SectionID=245"
    },
    {
      "id": "ksa_moh_official",
      "name": "KSA Ministry of Health Official News",
      "type": "rss",
      "enabled": true,
      "url": "https://www.moh.gov.sa/_layouts/15/listfeed.aspx?List=%7B5A0C8360-6F88-4F8A-A0A5-502C690E7F5A%7D"
    },
  ],
  "keywords": [
    "علاج بالأعشاب",
    "فوائد صحية",
    "طب بديل",
    "الصحة في السعودية",
    "العناية الطبيعية"
  ],
  "blocked_keywords": [
    "معجزة",
    "شفاء نهائي",
    "علاج مضمون",
    "بدون طبيب"
  ],
  "default": {
    "language": "ar",
    "country": "sa",
    "category": "health",
    "deep_search_minimum": 0
  }
}
  }
}
